source_weatherstack/__init__.py
source_weatherstack/manifest.yaml
source_weatherstack/run.py
source_weatherstack/source.py
airbyte_source_weatherstack-1.0.2.dist-info/METADATA
airbyte_source_weatherstack-1.0.2.dist-info/WHEEL
airbyte_source_weatherstack-1.0.2.dist-info/entry_points.txt
airbyte_source_weatherstack-1.0.2.dist-info/RECORD
