Metadata-Version: 2.1
Name: airbyte-source-weatherstack
Version: 1.0.2
Summary: Source implementation for Weatherstack.
Home-page: https://airbyte.com
License: MIT
Author: Airbyte
Author-email: contact@airbyte.io
Requires-Python: >=3.10,<4.0
Classifier: License :: OSI Approved :: MIT License
Classifier: Programming Language :: Python :: 3
Classifier: Programming Language :: Python :: 3.10
Classifier: Programming Language :: Python :: 3.11
Classifier: Programming Language :: Python :: 3.12
Requires-Dist: airbyte-cdk (>=4.0.1,<5.0.0)
Project-URL: Documentation, https://docs.airbyte.com/integrations/sources/weatherstack
Project-URL: Repository, https://github.com/airbytehq/airbyte
